python_cdp/__init__.py
python_cdp/_commandline.py
python_cdp/_const.py
python_cdp/_headers.py
python_cdp/_mixins.py
python_cdp/_models.py
python_cdp/_protocols.py
python_cdp/_templates.py
python_cdp/_types.py
python_cdp/_utils.py
python_cdp/cdp/__init__.py
python_cdp/cdp/accessibility.py
python_cdp/cdp/animation.py
python_cdp/cdp/audits.py
python_cdp/cdp/background_service.py
python_cdp/cdp/browser.py
python_cdp/cdp/cache_storage.py
python_cdp/cdp/cast.py
python_cdp/cdp/console.py
python_cdp/cdp/css.py
python_cdp/cdp/database.py
python_cdp/cdp/debugger.py
python_cdp/cdp/device_access.py
python_cdp/cdp/device_orientation.py
python_cdp/cdp/dom.py
python_cdp/cdp/dom_debugger.py
python_cdp/cdp/dom_snapshot.py
python_cdp/cdp/dom_storage.py
python_cdp/cdp/emulation.py
python_cdp/cdp/event_breakpoints.py
python_cdp/cdp/fed_cm.py
python_cdp/cdp/fetch.py
python_cdp/cdp/headless_experimental.py
python_cdp/cdp/heap_profiler.py
python_cdp/cdp/indexed_db.py
python_cdp/cdp/input.py
python_cdp/cdp/inspector.py
python_cdp/cdp/io.py
python_cdp/cdp/layer_tree.py
python_cdp/cdp/log.py
python_cdp/cdp/media.py
python_cdp/cdp/memory.py
python_cdp/cdp/network.py
python_cdp/cdp/overlay.py
python_cdp/cdp/page.py
python_cdp/cdp/performance.py
python_cdp/cdp/performance_timeline.py
python_cdp/cdp/preload.py
python_cdp/cdp/profiler.py
python_cdp/cdp/runtime.py
python_cdp/cdp/schema.py
python_cdp/cdp/security.py
python_cdp/cdp/service_worker.py
python_cdp/cdp/storage.py
python_cdp/cdp/system_info.py
python_cdp/cdp/target.py
python_cdp/cdp/tethering.py
python_cdp/cdp/tracing.py
python_cdp/cdp/utils.py
python_cdp/cdp/web_audio.py
python_cdp/cdp/web_authn.py
python_cdp/client/__init__.py
python_cdp/client/client.py
python_cdp/generate.py
python_cdp-0.3.0.dist-info/LICENSE
python_cdp-0.3.0.dist-info/METADATA
python_cdp-0.3.0.dist-info/WHEEL
python_cdp-0.3.0.dist-info/RECORD
