Metadata-Version: 2.1
Name: python-cdp
Version: 0.3.0
Summary: Python library for interacting with the chrome devtools protocol
Author: symonk
Author-email: jackofspaces@gmail.com
Requires-Python: >=3.9,<4.0
Classifier: Programming Language :: Python :: 3
Classifier: Programming Language :: Python :: 3.9
Classifier: Programming Language :: Python :: 3.10
Classifier: Programming Language :: Python :: 3.11
Requires-Dist: loguru (>=0.6.0,<0.7.0)
Requires-Dist: websockets (>=10.4,<11.0)
